skleern.py
skleern-0.0.2.dist-info/METADATA
skleern-0.0.2.dist-info/WHEEL
skleern-0.0.2.dist-info/top_level.txt
skleern-0.0.2.dist-info/RECORD
