Metadata-Version: 2.1
Name: skleern
Version: 0.0.2
Summary: sample
Home-page: UNKNOWN
Author: as
License: UNKNOWN
Platform: UNKNOWN
Classifier: Programming Language :: Python :: 3
Classifier: License :: OSI Approved :: MIT License
Classifier: Operating System :: OS Independent
Requires-Python: >=3.6
